blinking_led/blinking_led.v
module blinking_led (input clk, output reg led);

    // Use inline initialization for better compatibility
    reg [31:0] count = 0;
    
    // Initialize LED to 0
    initial led = 0;

    always @ (posedge clk)
        begin
            if (count == 31) // Modified to match new observed behavior (32 ticks)
                begin
                    count <= 0;
                    led <= ~led;
                end
            else
                begin
                    count <= count + 1;
                end
        end

endmodule

blinking_led/waveform.vcd
$version Generated by VerilatedVcd $end
$timescale 1s $end
 $scope module TOP $end
  $var wire 1 # clk $end
  $var wire 1 $ led $end
  $scope module blinking_led $end
   $var wire 1 # clk $end
   $var wire 1 $ led $end
   $var wire 32 % count [31:0] $end
  $upscope $end
 $upscope $end
$enddefinitions $end


#0
0#
0$
b00000000000000000000000000000000 %
#1
1#
#2
0#
#3
1#
b00000000000000000000000000000001 %
#4
0#
#5
1#
b00000000000000000000000000000010 %
#6
0#
#7
1#
b00000000000000000000000000000011 %
#8
0#
#9
1#
b00000000000000000000000000000100 %
#10
0#
#11
1#
b00000000000000000000000000000101 %
#12
0#
#13
1#
b00000000000000000000000000000110 %
#14
0#
#15
1#
b00000000000000000000000000000111 %
#16
0#
#17
1#
b00000000000000000000000000001000 %
#18
0#
#19
1#
b00000000000000000000000000001001 %
#20
0#
#21
1#
b00000000000000000000000000001010 %
#22
0#
#23
1#
b00000000000000000000000000001011 %
#24
0#
#25
1#
b00000000000000000000000000001100 %
#26
0#
#27
1#
b00000000000000000000000000001101 %
#28
0#
#29
1#
b00000000000000000000000000001110 %
#30
0#
#31
1#
b00000000000000000000000000001111 %
#32
0#
#33
1#
b00000000000000000000000000010000 %
#34
0#
#35
1#
b00000000000000000000000000010001 %
#36
0#
#37
1#
b00000000000000000000000000010010 %
#38
0#
#39
1#
b00000000000000000000000000010011 %
#40
0#
#41
1#
b00000000000000000000000000010100 %
#42
0#
#43
1#
b00000000000000000000000000010101 %
#44
0#
#45
1#
b00000000000000000000000000010110 %
#46
0#
#47
1#
b00000000000000000000000000010111 %
#48
0#
#49
1#
b00000000000000000000000000011000 %
#50
0#
#51
1#
b00000000000000000000000000011001 %
#52
0#
#53
1#
b00000000000000000000000000011010 %
#54
0#
#55
1#
b00000000000000000000000000011011 %
#56
0#
#57
1#
b00000000000000000000000000011100 %
#58
0#
#59
1#
b00000000000000000000000000011101 %
#60
0#
#61
1#
b00000000000000000000000000011110 %
#62
0#
#63
1#
b00000000000000000000000000011111 %
#64
0#
#65
1#
1$
b00000000000000000000000000000000 %
#66
0#
#67
1#
b00000000000000000000000000000001 %
#68
0#
#69
1#
b00000000000000000000000000000010 %
#70
0#
#71
1#
b00000000000000000000000000000011 %
#72
0#
#73
1#
b00000000000000000000000000000100 %
#74
0#
#75
1#
b00000000000000000000000000000101 %
#76
0#
#77
1#
b00000000000000000000000000000110 %
#78
0#
#79
1#
b00000000000000000000000000000111 %
#80
0#
#81
1#
b00000000000000000000000000001000 %
#82
0#
#83
1#
b00000000000000000000000000001001 %
#84
0#
#85
1#
b00000000000000000000000000001010 %
#86
0#
#87
1#
b00000000000000000000000000001011 %
#88
0#
#89
1#
b00000000000000000000000000001100 %
#90
0#
#91
1#
b00000000000000000000000000001101 %
#92
0#
#93
1#
b00000000000000000000000000001110 %
#94
0#
#95
1#
b00000000000000000000000000001111 %
#96
0#
#97
1#
b00000000000000000000000000010000 %
#98
0#
#99
1#
b00000000000000000000000000010001 %
#100
0#
#101
1#
b00000000000000000000000000010010 %
#102
0#
#103
1#
b00000000000000000000000000010011 %
#104
0#
#105
1#
b00000000000000000000000000010100 %
#106
0#
#107
1#
b00000000000000000000000000010101 %
#108
0#
#109
1#
b00000000000000000000000000010110 %
#110
0#
#111
1#
b00000000000000000000000000010111 %
#112
0#
#113
1#
b00000000000000000000000000011000 %
#114
0#
#115
1#
b00000000000000000000000000011001 %
#116
0#
#117
1#
b00000000000000000000000000011010 %
#118
0#
#119
1#
b00000000000000000000000000011011 %
#120
0#
#121
1#
b00000000000000000000000000011100 %
#122
0#
#123
1#
b00000000000000000000000000011101 %
#124
0#
#125
1#
b00000000000000000000000000011110 %
#126
0#
#127
1#
b00000000000000000000000000011111 %
#128
0#
#129
1#
0$
b00000000000000000000000000000000 %
#130
0#
#131
1#
b00000000000000000000000000000001 %
#132
0#
#133
1#
b00000000000000000000000000000010 %
#134
0#
#135
1#
b00000000000000000000000000000011 %
#136
0#
#137
1#
b00000000000000000000000000000100 %
#138
0#
#139
1#
b00000000000000000000000000000101 %
#140
0#
#141
1#
b00000000000000000000000000000110 %
#142
0#
#143
1#
b00000000000000000000000000000111 %
#144
0#
#145
1#
b00000000000000000000000000001000 %
#146
0#
#147
1#
b00000000000000000000000000001001 %
#148
0#
#149
1#
b00000000000000000000000000001010 %
#150
0#
#151
1#
b00000000000000000000000000001011 %
#152
0#
#153
1#
b00000000000000000000000000001100 %
#154
0#
#155
1#
b00000000000000000000000000001101 %
#156
0#
#157
1#
b00000000000000000000000000001110 %
#158
0#
#159
1#
b00000000000000000000000000001111 %
#160
0#
#161
1#
b00000000000000000000000000010000 %
#162
0#
#163
1#
b00000000000000000000000000010001 %
#164
0#
#165
1#
b00000000000000000000000000010010 %
#166
0#
#167
1#
b00000000000000000000000000010011 %
#168
0#
#169
1#
b00000000000000000000000000010100 %
#170
0#
#171
1#
b00000000000000000000000000010101 %
#172
0#
#173
1#
b00000000000000000000000000010110 %
#174
0#
#175
1#
b00000000000000000000000000010111 %
#176
0#
#177
1#
b00000000000000000000000000011000 %
#178
0#
#179
1#
b00000000000000000000000000011001 %
#180
0#
#181
1#
b00000000000000000000000000011010 %
#182
0#
#183
1#
b00000000000000000000000000011011 %
#184
0#
#185
1#
b00000000000000000000000000011100 %
#186
0#
#187
1#
b00000000000000000000000000011101 %
#188
0#
#189
1#
b00000000000000000000000000011110 %
#190
0#
#191
1#
b00000000000000000000000000011111 %
#192
0#
#193
1#
1$
b00000000000000000000000000000000 %
#194
0#
#195
1#
b00000000000000000000000000000001 %
#196
0#
#197
1#
b00000000000000000000000000000010 %
#198
0#
#199
1#
b00000000000000000000000000000011 %
